swagd/__init__.py
swagd/__main__.py
swagd/ui/favicon-16x16.png
swagd/ui/favicon-32x32.png
swagd/ui/index.css
swagd/ui/index.html
swagd/ui/oauth2-redirect.html
swagd/ui/swagger-initializer.js
swagd/ui/swagger-ui-bundle.js
swagd/ui/swagger-ui-bundle.js.map
swagd/ui/swagger-ui-es-bundle-core.js
swagd/ui/swagger-ui-es-bundle-core.js.map
swagd/ui/swagger-ui-es-bundle.js
swagd/ui/swagger-ui-es-bundle.js.map
swagd/ui/swagger-ui-standalone-preset.js
swagd/ui/swagger-ui-standalone-preset.js.map
swagd/ui/swagger-ui.css
swagd/ui/swagger-ui.css.map
swagd/ui/swagger-ui.js
swagd/ui/swagger-ui.js.map
swagd-5.2.1.dist-info/LICENSE
swagd-5.2.1.dist-info/METADATA
swagd-5.2.1.dist-info/WHEEL
swagd-5.2.1.dist-info/entry_points.txt
swagd-5.2.1.dist-info/top_level.txt
swagd-5.2.1.dist-info/RECORD
