Metadata-Version: 2.1
Name: swagd
Version: 5.2.1
Summary: Swagger UI Server
Author-email: Gerhard Tan <gwohau.tan@gmail.com>
License: Apache License
Project-URL: Homepage, https://github.com/koho/swagd
Project-URL: Bug Tracker, https://github.com/koho/swagd/issues
Classifier: Programming Language :: Python :: 3
Classifier: License :: OSI Approved :: MIT License
Classifier: Operating System :: OS Independent
Requires-Python: >=3.5
License-File: LICENSE
Requires-Dist: PyYAML (>=5.1)
